[
  {
    "pregunta": "¿Cuál es la función principal de los glóbulos rojos?",
    "opciones": [
      "Transportar dióxido de carbono desde los tejidos a los pulmones",
      "Luchar contra infecciones",
      "Transportar oxígeno desde los pulmones hacia los tejidos",
      "Regular la temperatura corporal"
    ],
    "respuestaCorrecta": "Transportar oxígeno desde los pulmones hacia los tejidos",
    "explicacion": "Los glóbulos rojos contienen hemoglobina, una proteína que se une al oxígeno para transportarlo desde los pulmones hacia todas las células del cuerpo.",
    "categoria": "Medicina"
  },
  {
    "pregunta": "¿Cuál es el órgano responsable de filtrar la sangre y producir orina?",
    "opciones": [
      "Hígado",
      "Riñón",
      "Pulmón",
      "Páncreas"
    ],
    "respuestaCorrecta": "Riñón",
    "explicacion": "El riñón filtra la sangre para eliminar desechos y exceso de agua, formando orina.",
    "categoria": "Anatomía"
  },
  {
    "pregunta": "¿Qué elemento tiene el símbolo 'Na' en la tabla periódica?",
    "opciones": [
      "Nitrógeno",
      "Neón",
      "Sodio",
      "Níquel"
    ],
    "respuestaCorrecta": "Sodio",
    "explicacion": "El símbolo 'Na' proviene del latín 'Natrium', que significa sodio.",
    "categoria": "Química"
  },
  {
    "pregunta": "¿Qué es el ADN?",
    "opciones": [
      "Una proteína que transporta oxígeno",
      "Un tipo de célula del sistema inmune",
      "El material genético que contiene las instrucciones para el desarrollo y funcionamiento de los organismos",
      "Un ácido involucrado en la digestión"
    ],
    "respuestaCorrecta": "El material genético que contiene las instrucciones para el desarrollo y funcionamiento de los organismos",
    "explicacion": "El ADN (ácido desoxirribonucleico) contiene los genes que dirigen cómo funciona un organismo.",
    "categoria": "Biología"
  },
  {
    "pregunta": "¿Qué tipo de tejido conecta los músculos a los huesos?",
    "opciones": [
      "Ligamentos",
      "Tendones",
      "Cartílago",
      "Fascia"
    ],
    "respuestaCorrecta": "Tendones",
    "explicacion": "Los tendones son estructuras fibrosas que conectan los músculos con los huesos, permitiendo el movimiento.",
    "categoria": "Anatomía"
  },
  {
    "pregunta": "¿Qué sistema del cuerpo humano se encarga de defendernos contra infecciones?",
    "opciones": [
      "Sistema digestivo",
      "Sistema respiratorio",
      "Sistema inmunológico",
      "Sistema circulatorio"
    ],
    "respuestaCorrecta": "Sistema inmunológico",
    "explicacion": "El sistema inmunológico incluye células y órganos que nos protegen de bacterias, virus y otros patógenos.",
    "categoria": "Medicina"
  },
  {
    "pregunta": "¿Cómo se llama el proceso mediante el cual las plantas convierten la luz solar en energía?",
    "opciones": [
      "Transpiración",
      "Fotosíntesis",
      "Respiración celular",
      "Fermentación"
    ],
    "respuestaCorrecta": "Fotosíntesis",
    "explicacion": "La fotosíntesis es el proceso por el cual las plantas convierten dióxido de carbono y agua en glucosa y oxígeno usando la luz solar.",
    "categoria": "Biología"
  },
  {
    "pregunta": "¿Cuál es la fórmula química del dióxido de carbono?",
    "opciones": [
      "H2O",
      "CO",
      "CO2",
      "CH4"
    ],
    "respuestaCorrecta": "CO2",
    "explicacion": "CO2 representa una molécula de dióxido de carbono, que contiene un átomo de carbono y dos de oxígeno.",
    "categoria": "Química"
  }
]
